cerberus/__init__.py
cerberus/errors.py
cerberus/platform.py
cerberus/schema.py
cerberus/utils.py
cerberus/validator.py
Cerberus-1.3.6.dist-info/AUTHORS
Cerberus-1.3.6.dist-info/LICENSE
Cerberus-1.3.6.dist-info/METADATA
Cerberus-1.3.6.dist-info/WHEEL
Cerberus-1.3.6.dist-info/top_level.txt
Cerberus-1.3.6.dist-info/RECORD
