Metadata-Version: 2.1
Name: Cerberus
Version: 1.3.6
Summary: Lightweight, extensible schema and data validation tool for Pythondictionaries.
Author-email: Nicola Iarocci <nicola@nicolaiarocci.com>
Maintainer-email: Frank Sachsenheim <funkyfuture@riseup.net>
License: ISC License
Project-URL: Documentation, http://docs.python-cerberus.org
Project-URL: Repository, https://github.com/pyeve/cerberus
Keywords: validation,schema,dictionaries,documents,normalization
Classifier: Development Status :: 5 - Production/Stable
Classifier: Intended Audience :: Developers
Classifier: Natural Language :: English
Classifier: License :: OSI Approved :: ISC License (ISCL)
Classifier: Operating System :: OS Independent
Classifier: Programming Language :: Python
Classifier: Programming Language :: Python :: 3
Classifier: Programming Language :: Python :: 3.7
Classifier: Programming Language :: Python :: 3.8
Classifier: Programming Language :: Python :: 3.9
Classifier: Programming Language :: Python :: 3.10
Classifier: Programming Language :: Python :: 3.11
Classifier: Programming Language :: Python :: 3.12
Classifier: Programming Language :: Python :: 3.13
Classifier: Programming Language :: Python :: Implementation :: CPython
Classifier: Programming Language :: Python :: Implementation :: PyPy
Requires-Python: >=3.7
License-File: LICENSE
License-File: AUTHORS
Requires-Dist: importlib-metadata; python_version < "3.8"
